abs_schema/__init__.py
abs_schema/fields_schema/__init__.py
abs_schema/fields_schema/common_schema.py
abs_schema/fields_schema/field_schema.py
abs_schema/libs/__init__.py
abs_schema/libs/extend_enum.py
abs_schema/libs/make_optional.py
abs_schema-0.1.0.dist-info/METADATA
abs_schema-0.1.0.dist-info/WHEEL
abs_schema-0.1.0.dist-info/RECORD
