Metadata-Version: 2.3
Name: abs-schema
Version: 0.1.0
Summary: AutoBridge Systems Schema Library
Author: AutoBridgeSystems
Author-email: info@autobridgesystems.com
Requires-Python: >=3.11,<4.0
Classifier: Programming Language :: Python :: 3
Classifier: Programming Language :: Python :: 3.11
Classifier: Programming Language :: Python :: 3.12
Classifier: Programming Language :: Python :: 3.13
Requires-Dist: abs-exception-core (>=0.2.0,<0.3.0)
